miniav/__init__.py
miniav/_miniav_base.py
miniav/_version.py
miniav/db.py
miniav/dev.py
miniav/ros/__init__.py
miniav/ros/messages.py
miniav/utils/__init__.py
miniav/utils/files.py
miniav/utils/logger.py
miniav/utils/yaml_parser.py
miniav-0.0.9.dist-info/LICENSE.txt
miniav-0.0.9.dist-info/METADATA
miniav-0.0.9.dist-info/WHEEL
miniav-0.0.9.dist-info/entry_points.txt
miniav-0.0.9.dist-info/top_level.txt
miniav-0.0.9.dist-info/RECORD
