Metadata-Version: 2.1
Name: miniav
Version: 0.0.9
Summary: MiniAV Project
Home-page: UNKNOWN
Author: UW Simulation Based Engineering Lab
License: BSD3
Project-URL: Homepage, https://uwsbel.github.io/miniav
Project-URL: Bug Reports, https://github.com/uwsbel/miniav/issues
Project-URL: Source Code, https://github.com/uwsbel/miniav/
Project-URL: Our Lab!, https://sbel.wisc.edu
Platform: UNKNOWN
Classifier: Development Status :: 3 - Alpha
Classifier: Topic :: Software Development
Classifier: License :: OSI Approved :: MIT License
Classifier: Programming Language :: Python :: 3
Requires-Python: >=3.8.2, <4
License-File: LICENSE.txt
Requires-Dist: python-magic (==0.4.24)
Requires-Dist: rosbags (==0.9.6)
Requires-Dist: pyyaml (==6.0)
Requires-Dist: python-on-whales (==0.35.0)
Requires-Dist: pandas (==1.3.4)
Requires-Dist: colorlog (==6.6.0)
